imgtobase64/__init__.py
imgtobase64/job.py
imgtobase64-1.1.1.dist-info/LICENCE
imgtobase64-1.1.1.dist-info/METADATA
imgtobase64-1.1.1.dist-info/WHEEL
imgtobase64-1.1.1.dist-info/top_level.txt
imgtobase64-1.1.1.dist-info/RECORD
