Metadata-Version: 2.1
Name: imgtobase64
Version: 1.1.1
Summary: Convert your image url from web or your image field from database to base64
Home-page: https://github.com/VolkenoMakers/imgtobase64
Author: VOLKENO
Author-email: contact@volkeno-tank.com
License: MIT
Keywords: core package
Platform: UNKNOWN
Classifier: Development Status :: 5 - Production/Stable
Classifier: License :: OSI Approved :: MIT License
Classifier: Programming Language :: Python :: 3
Classifier: Operating System :: OS Independent
Classifier: Intended Audience :: Developers
License-File: LICENCE
Requires-Dist: imgtobase64
